typer2ui/__init__.py
typer2ui/context.py
typer2ui/data_source.py
typer2ui/events.py
typer2ui/hold.py
typer2ui/output.py
typer2ui/spec_builder.py
typer2ui/specs.py
typer2ui/state.py
typer2ui/ui_app.py
typer2ui/runners/__init__.py
typer2ui/runners/base.py
typer2ui/runners/cli_context.py
typer2ui/runners/cli_runner.py
typer2ui/runners/gui_context.py
typer2ui/runners/gui_runner.py
typer2ui/ui_blocks/__init__.py
typer2ui/ui_blocks/base.py
typer2ui/ui_blocks/data_table.py
typer2ui/ui_blocks/interactive.py
typer2ui/ui_blocks/layout.py
typer2ui/ui_blocks/md.py
typer2ui/ui_blocks/print.py
typer2ui/ui_blocks/table.py
typer2ui/ui_blocks/tabs.py
typer2ui/ui_blocks/text.py
typer2ui-0.15.1.dist-info/licenses/LICENSE
typer2ui-0.15.1.dist-info/METADATA
typer2ui-0.15.1.dist-info/WHEEL
typer2ui-0.15.1.dist-info/top_level.txt
typer2ui-0.15.1.dist-info/RECORD
