Metadata-Version: 2.4
Name: typer2ui
Version: 0.15.1
Summary: Automatically generate desktop GUIs for Typer CLI applications using Flet
Author: Typer2UI Contributors
License: MIT
Project-URL: Homepage, https://github.com/rados4y/typer2ui
Project-URL: Repository, https://github.com/rados4y/typer2ui
Project-URL: Issues, https://github.com/rados4y/typer2ui/issues
Keywords: typer,cli,gui,flet,desktop,ui
Classifier: Development Status :: 3 - Alpha
Classifier: Intended Audience :: Developers
Classifier: License :: OSI Approved :: MIT License
Classifier: Programming Language :: Python :: 3
Classifier: Programming Language :: Python :: 3.10
Classifier: Programming Language :: Python :: 3.11
Classifier: Programming Language :: Python :: 3.12
Classifier: Topic :: Software Development :: User Interfaces
Classifier: Topic :: Software Development :: Libraries :: Python Modules
Requires-Python: >=3.10
License-File: LICENSE
Requires-Dist: typer>=0.9.0
Requires-Dist: flet>=0.80.1
Provides-Extra: dev
Requires-Dist: pytest>=7.0.0; extra == "dev"
Requires-Dist: mypy>=1.0.0; extra == "dev"
Dynamic: license-file
